scr/calculatorpackage_harimythily/__init__.py
scr/calculatorpackage_harimythily/example.py
calculatorpackage_harimythily-0.0.1.dist-info/METADATA
calculatorpackage_harimythily-0.0.1.dist-info/WHEEL
calculatorpackage_harimythily-0.0.1.dist-info/licenses/LICENSE.txt.txt
calculatorpackage_harimythily-0.0.1.dist-info/RECORD
