Metadata-Version: 2.1
Name: calculatorpackage_harimythily
Version: 0.0.1
Summary: To add,subtract,multiply and divide two numbers
Author-email: haripriya <hr972439@gmail.com>
License-File: LICENSE.txt.txt
Classifier: License :: OSI Approved :: MIT License
Classifier: Operating System :: OS Independent
Classifier: Programming Language :: Python :: 3
Requires-Python: >=3.7
